guiml/__init__.py
guiml/_components.py
guiml/components.py
guiml/core.py
guiml/injectables.py
guiml/layout.py
guiml/plugins.py
guiml/registry.py
guiml/resources.py
guiml/transformer.py
guimlcomponents/base/__init__.py
guimlcomponents/base/container.py
guimlcomponents/base/image.py
guimlcomponents/base/layout.py
guimlcomponents/base/shared.py
guimlcomponents/base/styles.yml
guimlcomponents/base/text.py
guimlcomponents/base/window.py
guimlcomponents/base/cairocffi_to_pycairo/LICENSE
guimlcomponents/base/cairocffi_to_pycairo/__init__.py
guiml-0.2.0.dist-info/METADATA
guiml-0.2.0.dist-info/WHEEL
guiml-0.2.0.dist-info/licenses/LICENSE
guiml-0.2.0.dist-info/RECORD
