Metadata-Version: 2.4
Name: guiml
Version: 0.2.0
Summary: An xml based GUI framework with property binding and dependency injection.
Project-URL: Homepage, https://github.com/StephanGocht/guiml
Project-URL: Issues, https://github.com/StephanGocht/guiml/issues
Project-URL: Documentation, http://guiml.readthedocs.io/
Author-email: Stephan Gocht <gocht@mailbox.org>
License-File: LICENSE
Classifier: License :: OSI Approved :: MIT License
Classifier: Operating System :: OS Independent
Classifier: Programming Language :: Python :: 3
Requires-Python: >=3.9
Requires-Dist: cairocffi
Requires-Dist: pangocairocffi
Requires-Dist: pangocffi
Requires-Dist: pycairo
Requires-Dist: pyglet
Requires-Dist: pygobject
Requires-Dist: pyyaml
